unireo/__init__.py
unireo/calib/__init__.py
unireo/calib/calib_data.py
unireo/calib/load_calib_mat.py
unireo/calib/mono_calib.py
unireo/calib/save_calib_mat.py
unireo/calib/stereo_calib.py
unireo/cam_info/__init__.py
unireo/cam_info/cam_ctrl.py
unireo/cam_info/cam_params.py
unireo/drawing/__init__.py
unireo/drawing/shape.py
unireo/drawing/text.py
unireo/err_proc/__init__.py
unireo/err_proc/error_code.py
unireo/err_proc/exceptions.py
unireo/spatial/__init__.py
unireo/spatial/depth.py
unireo/utils/__init__.py
unireo/utils/extensions.py
unireo/utils/shared_vars.py
unireo-0.1.2.dist-info/METADATA
unireo-0.1.2.dist-info/WHEEL
unireo-0.1.2.dist-info/top_level.txt
unireo-0.1.2.dist-info/RECORD
