Metadata-Version: 2.1
Name: unireo
Version: 0.1.2
Summary: A universal SDK for synchronized dual-eye cameras compliant with the UVC protocol
Home-page: https://github.com/Anawaert/unireo
Author: Anawaert
Author-email: anawaertstudio@outlook.com
Platform: all
Classifier: Intended Audience :: Developers
Classifier: Operating System :: OS Independent
Classifier: Natural Language :: Chinese (Simplified)
Classifier: Programming Language :: Python
Classifier: Programming Language :: Python :: 3.6
Classifier: Programming Language :: Python :: 3.7
Classifier: Programming Language :: Python :: 3.8
Classifier: Programming Language :: Python :: 3.9
Classifier: Programming Language :: Python :: 3.10
Classifier: Topic :: Software Development :: Libraries
